code_creator/__init__.py
code_creator/expression_graph.py
code_creator/math.py
code_creator/symbols.py
code_creator-0.0.1.dist-info/LICENSE
code_creator-0.0.1.dist-info/METADATA
code_creator-0.0.1.dist-info/WHEEL
code_creator-0.0.1.dist-info/top_level.txt
code_creator-0.0.1.dist-info/RECORD
