Metadata-Version: 2.1
Name: code-creator
Version: 0.0.1
Summary: tracks operations in python at runtime and converts them back into source code --> code dynamization
Home-page: https://gitlab.com/berlinade/code-creator
Author: codima
License: GPLv3
Project-URL: doc, https://berlinade.gitlab.io/code-creator/
Platform: unix
Platform: linux
Classifier: Development Status :: 3 - Alpha
Classifier: License :: OSI Approved :: GNU General Public License v3 (GPLv3)
Classifier: Operating System :: OS Independent
Classifier: Programming Language :: Python :: 3
Classifier: Programming Language :: Python :: 3 :: Only
Classifier: Programming Language :: Python :: 3.10
Requires-Python: >=3.10
License-File: LICENSE
Requires-Dist: numpy
